pictriage
