Metadata-Version: 1.0
Name: pictriage
Version: 1.0.6
Summary: Description of my package
Home-page: UNKNOWN
Author: Author Name
Author-email: author@example.com
License: UNKNOWN
Platform: UNKNOWN
